{
  "abilities": [
    {
      "id": "fire_strike",
      "name": "Fire Strike",
      "description": "A fiery basic attack that restores MP",
      "type": "BasicAttack",
      "target": "SingleEnemy",
      "mpCostPercent": 0,
      "mpRestorePercent": 20,
      "hpCostPercent": 0,
      "basePower": 12,
      "element": "Fire",
      "statusEffect": "",
      "statusChance": 0,
      "duration": 0,
      "isMultiHit": false,
      "hitCount": 1,
      "canCrit": true,
      "critChance": 0.1,
      "critMultiplier": 1.5,
      "isCleanse": false,
      "statusEffect2": "",
      "statusChance2": 0,
      "duration2": 0,
      "selfStatusEffect": "",
      "selfDuration": 0,
      "selfMagnitude": 0
    },
    {
      "id": "bramble_bind",
      "name": "Bramble Bind",
      "description": "Entangling vines that damage and root the target",
      "type": "DamageSkill",
      "target": "SingleEnemy",
      "mpCostPercent": 25,
      "mpRestorePercent": 0,
      "hpCostPercent": 0,
      "basePower": 15,
      "element": "Nature",
      "statusEffect": "Rooted",
      "statusChance": 0.8,
      "duration": 2,
      "isMultiHit": false,
      "hitCount": 1,
      "canCrit": false,
      "critChance": 0,
      "critMultiplier": 1,
      "isCleanse": false,
      "statusEffect2": "",
      "statusChance2": 0,
      "duration2": 0,
      "selfStatusEffect": "",
      "selfDuration": 0,
      "selfMagnitude": 0
    },
    {
      "id": "echo_verse",
      "name": "Echo Verse",
      "description": "A resonating verse that bolsters an ally's defense",
      "type": "BuffSkill",
      "target": "SingleAlly",
      "mpCostPercent": 40,
      "mpRestorePercent": 0,
      "hpCostPercent": 0,
      "basePower": 1.5,
      "element": "Neutral",
      "statusEffect": "DefenseBuff",
      "statusChance": 1.0,
      "duration": 2,
      "isMultiHit": false,
      "hitCount": 1,
      "canCrit": false,
      "critChance": 0,
      "critMultiplier": 1,
      "isCleanse": false,
      "statusEffect2": "",
      "statusChance2": 0,
      "duration2": 0,
      "selfStatusEffect": "",
      "selfDuration": 0,
      "selfMagnitude": 0
    },
    {
      "id": "hunters_mark",
      "name": "Hunters Mark",
      "description": "Marks the target so allies deal bonus damage",
      "type": "DebuffSkill",
      "target": "SingleEnemy",
      "mpCostPercent": 20,
      "mpRestorePercent": 0,
      "hpCostPercent": 0,
      "basePower": 0,
      "element": "Neutral",
      "statusEffect": "Marked",
      "statusChance": 1.0,
      "duration": 3,
      "isMultiHit": false,
      "hitCount": 1,
      "canCrit": false,
      "critChance": 0,
      "critMultiplier": 1,
      "isCleanse": false,
      "statusEffect2": "",
      "statusChance2": 0,
      "duration2": 0,
      "selfStatusEffect": "",
      "selfDuration": 0,
      "selfMagnitude": 0
    },
    {
      "id": "hail_of_arrows",
      "name": "Hail of Arrows",
      "description": "A barrage of arrows raining down on all enemies",
      "type": "DamageSkill",
      "target": "AllEnemies",
      "mpCostPercent": 50,
      "mpRestorePercent": 0,
      "hpCostPercent": 0,
      "basePower": 10,
      "element": "Neutral",
      "statusEffect": "",
      "statusChance": 0,
      "duration": 0,
      "isMultiHit": true,
      "hitCount": 3,
      "canCrit": true,
      "critChance": 0.1,
      "critMultiplier": 1.5,
      "isCleanse": false,
      "statusEffect2": "",
      "statusChance2": 0,
      "duration2": 0,
      "selfStatusEffect": "",
      "selfDuration": 0,
      "selfMagnitude": 0
    },
    {
      "id": "wind_gust",
      "name": "Wind Gust",
      "description": "A swift gust of wind that restores MP",
      "type": "BasicAttack",
      "target": "SingleEnemy",
      "mpCostPercent": 0,
      "mpRestorePercent": 20,
      "hpCostPercent": 0,
      "basePower": 10,
      "element": "Air",
      "statusEffect": "",
      "statusChance": 0,
      "duration": 0,
      "isMultiHit": false,
      "hitCount": 1,
      "canCrit": true,
      "critChance": 0.1,
      "critMultiplier": 1.5,
      "isCleanse": false,
      "statusEffect2": "",
      "statusChance2": 0,
      "duration2": 0,
      "selfStatusEffect": "",
      "selfDuration": 0,
      "selfMagnitude": 0
    },
    {
      "id": "hayfever_haze",
      "name": "Hayfever Haze",
      "description": "A cloud of pollen that causes sneezing and blurred vision",
      "type": "DebuffSkill",
      "target": "AllEnemies",
      "mpCostPercent": 30,
      "mpRestorePercent": 0,
      "hpCostPercent": 0,
      "basePower": 0,
      "element": "Nature",
      "statusEffect": "Sneeze",
      "statusChance": 0.6,
      "duration": 2,
      "isMultiHit": false,
      "hitCount": 1,
      "canCrit": false,
      "critChance": 0,
      "critMultiplier": 1,
      "isCleanse": false,
      "statusEffect2": "AccuracyDown",
      "statusChance2": 0.6,
      "duration2": 2,
      "selfStatusEffect": "",
      "selfDuration": 0,
      "selfMagnitude": 0
    },
    {
      "id": "herbal_remedy",
      "name": "Herbal Remedy",
      "description": "Heals an ally and cleanses status effects",
      "type": "HealSkill",
      "target": "SingleAlly",
      "mpCostPercent": 25,
      "mpRestorePercent": 0,
      "hpCostPercent": 0,
      "basePower": 35,
      "element": "Nature",
      "statusEffect": "",
      "statusChance": 0,
      "duration": 0,
      "isMultiHit": false,
      "hitCount": 1,
      "canCrit": false,
      "critChance": 0,
      "critMultiplier": 1,
      "isCleanse": true,
      "statusEffect2": "",
      "statusChance2": 0,
      "duration2": 0,
      "selfStatusEffect": "",
      "selfDuration": 0,
      "selfMagnitude": 0
    },
    {
      "id": "bloom_burst",
      "name": "Bloom Burst",
      "description": "Plants a flower trap on the enemy that triggers on hit and spreads",
      "type": "DebuffSkill",
      "target": "SingleEnemy",
      "mpCostPercent": 45,
      "mpRestorePercent": 0,
      "hpCostPercent": 0,
      "basePower": 15,
      "element": "Nature",
      "statusEffect": "FlowerTrap",
      "statusChance": 1.0,
      "duration": 3,
      "isMultiHit": false,
      "hitCount": 1,
      "canCrit": false,
      "critChance": 0,
      "critMultiplier": 1,
      "isCleanse": false,
      "statusEffect2": "",
      "statusChance2": 0,
      "duration2": 0,
      "selfStatusEffect": "",
      "selfDuration": 0,
      "selfMagnitude": 0
    },
    {
      "id": "stone_bash",
      "name": "Stone Bash",
      "description": "A heavy earthen strike that restores MP",
      "type": "BasicAttack",
      "target": "SingleEnemy",
      "mpCostPercent": 0,
      "mpRestorePercent": 20,
      "hpCostPercent": 0,
      "basePower": 14,
      "element": "Earth",
      "statusEffect": "",
      "statusChance": 0,
      "duration": 0,
      "isMultiHit": false,
      "hitCount": 1,
      "canCrit": true,
      "critChance": 0.1,
      "critMultiplier": 1.5,
      "isCleanse": false,
      "statusEffect2": "",
      "statusChance2": 0,
      "duration2": 0,
      "selfStatusEffect": "",
      "selfDuration": 0,
      "selfMagnitude": 0
    },
    {
      "id": "verdant_aegis",
      "name": "Verdant Aegis",
      "description": "Shields an ally with living bark that blocks 3 hits",
      "type": "BuffSkill",
      "target": "SingleAlly",
      "mpCostPercent": 30,
      "mpRestorePercent": 0,
      "hpCostPercent": 0,
      "basePower": 3,
      "element": "Nature",
      "statusEffect": "HitShield",
      "statusChance": 1.0,
      "duration": 99,
      "isMultiHit": false,
      "hitCount": 1,
      "canCrit": false,
      "critChance": 0,
      "critMultiplier": 1,
      "isCleanse": false,
      "statusEffect2": "",
      "statusChance2": 0,
      "duration2": 0,
      "selfStatusEffect": "",
      "selfDuration": 0,
      "selfMagnitude": 0
    },
    {
      "id": "runebark_resonance",
      "name": "Runebark Resonance",
      "description": "Shakes the earth damaging all enemies and taunting them to attack Thorn",
      "type": "DamageSkill",
      "target": "AllEnemies",
      "mpCostPercent": 35,
      "mpRestorePercent": 0,
      "hpCostPercent": 0,
      "basePower": 12,
      "element": "Earth",
      "statusEffect": "",
      "statusChance": 0,
      "duration": 0,
      "isMultiHit": false,
      "hitCount": 1,
      "canCrit": false,
      "critChance": 0,
      "critMultiplier": 1,
      "isCleanse": false,
      "statusEffect2": "",
      "statusChance2": 0,
      "duration2": 0,
      "selfStatusEffect": "Taunting",
      "selfDuration": 2,
      "selfMagnitude": 1
    },
    {
      "id": "heartwood_pulse",
      "name": "Heartwood Pulse",
      "description": "Ancient bark absorbs half of all incoming damage",
      "type": "BuffSkill",
      "target": "Self",
      "mpCostPercent": 40,
      "mpRestorePercent": 0,
      "hpCostPercent": 0,
      "basePower": 0,
      "element": "Nature",
      "statusEffect": "DamageAbsorb",
      "statusChance": 1.0,
      "duration": 3,
      "isMultiHit": false,
      "hitCount": 1,
      "canCrit": false,
      "critChance": 0,
      "critMultiplier": 1,
      "isCleanse": false,
      "statusEffect2": "",
      "statusChance2": 0,
      "duration2": 0,
      "selfStatusEffect": "",
      "selfDuration": 0,
      "selfMagnitude": 0
    },
    {
      "id": "root_swipe",
      "name": "Root Swipe",
      "description": "A powerful root strike that can immobilize",
      "type": "DamageSkill",
      "target": "SingleEnemy",
      "mpCostPercent": 0,
      "mpRestorePercent": 0,
      "hpCostPercent": 0,
      "basePower": 20,
      "element": "Nature",
      "statusEffect": "Rooted",
      "statusChance": 0.4,
      "duration": 2,
      "isMultiHit": false,
      "hitCount": 1,
      "canCrit": true,
      "critChance": 0.1,
      "critMultiplier": 1.5,
      "isCleanse": false,
      "statusEffect2": "",
      "statusChance2": 0,
      "duration2": 0,
      "selfStatusEffect": "",
      "selfDuration": 0,
      "selfMagnitude": 0
    },
    {
      "id": "spore_burst",
      "name": "Spore Burst",
      "description": "Toxic spores erupt hitting all enemies with poison and drowsiness",
      "type": "DamageSkill",
      "target": "AllEnemies",
      "mpCostPercent": 0,
      "mpRestorePercent": 0,
      "hpCostPercent": 0,
      "basePower": 14,
      "element": "Nature",
      "statusEffect": "Poisoned",
      "statusChance": 0.35,
      "duration": 3,
      "isMultiHit": false,
      "hitCount": 1,
      "canCrit": false,
      "critChance": 0,
      "critMultiplier": 1,
      "isCleanse": false,
      "statusEffect2": "Sleeping",
      "statusChance2": 0.25,
      "duration2": 2,
      "selfStatusEffect": "",
      "selfDuration": 0,
      "selfMagnitude": 0
    },
    {
      "id": "ancient_reflex",
      "name": "Ancient Reflex",
      "description": "The boss hardens its bark, reflecting 30% of incoming damage",
      "type": "BuffSkill",
      "target": "Self",
      "mpCostPercent": 0,
      "mpRestorePercent": 0,
      "hpCostPercent": 0,
      "basePower": 0.3,
      "element": "Earth",
      "statusEffect": "DamageReflect",
      "statusChance": 1.0,
      "duration": 2,
      "isMultiHit": false,
      "hitCount": 1,
      "canCrit": false,
      "critChance": 0,
      "critMultiplier": 1,
      "isCleanse": false,
      "statusEffect2": "",
      "statusChance2": 0,
      "duration2": 0,
      "selfStatusEffect": "",
      "selfDuration": 0,
      "selfMagnitude": 0
    }
  ]
}
